pydhis2/__init__.py
pydhis2/__main__.py
pydhis2/cli/__init__.py
pydhis2/cli/main.py
pydhis2/core/__init__.py
pydhis2/core/auth.py
pydhis2/core/cache.py
pydhis2/core/client.py
pydhis2/core/errors.py
pydhis2/core/rate_limit.py
pydhis2/core/retry.py
pydhis2/core/types.py
pydhis2/dqr/__init__.py
pydhis2/dqr/config.yml
pydhis2/dqr/metrics.py
pydhis2/endpoints/__init__.py
pydhis2/endpoints/analytics.py
pydhis2/endpoints/datavaluesets.py
pydhis2/endpoints/metadata.py
pydhis2/endpoints/tracker.py
pydhis2/io/__init__.py
pydhis2/io/arrow.py
pydhis2/io/schema.py
pydhis2/io/to_pandas.py
pydhis2/observe/__init__.py
pydhis2/observe/logging.py
pydhis2/observe/telemetry.py
pydhis2/pipeline/__init__.py
pydhis2/pipeline/config.py
pydhis2/pipeline/executor.py
pydhis2/pipeline/steps.py
pydhis2/templates/cookiecutter.json
pydhis2/templates/{{cookiecutter.project_slug}}/Makefile.cmd
pydhis2/templates/{{cookiecutter.project_slug}}/README.md
pydhis2/templates/{{cookiecutter.project_slug}}/env.example
pydhis2/templates/{{cookiecutter.project_slug}}/requirements.txt
pydhis2/templates/{{cookiecutter.project_slug}}/configs/dhis2.yml
pydhis2/templates/{{cookiecutter.project_slug}}/configs/dqr.yml
pydhis2/templates/{{cookiecutter.project_slug}}/pipelines/example.yml
pydhis2/templates/{{cookiecutter.project_slug}}/scripts/run_pipeline.py
pydhis2/testing/__init__.py
pydhis2/testing/benchmark_utils.py
pydhis2/testing/data_generator.py
pydhis2/testing/demo_test.py
pydhis2/testing/mock_server.py
pydhis2/testing/network_simulator.py
pydhis2-0.2.1.dist-info/licenses/LICENSE
pydhis2-0.2.1.dist-info/METADATA
pydhis2-0.2.1.dist-info/WHEEL
pydhis2-0.2.1.dist-info/entry_points.txt
pydhis2-0.2.1.dist-info/top_level.txt
pydhis2-0.2.1.dist-info/RECORD
