Metadata-Version: 2.4
Name: pydhis2
Version: 0.2.1
Summary: Reproducible DHIS2 Python SDK for LMIC scenarios
Author-email: pydhis2 contributors <pydhis2@github.com>
Maintainer-email: pydhis2 contributors <pydhis2@github.com>
License: Apache-2.0
Project-URL: Homepage, https://github.com/HzaCode/pyDHIS2
Project-URL: Documentation, https://hzacode.github.io/pyDHIS2
Project-URL: Repository, https://github.com/HzaCode/pyDHIS2
Project-URL: Issues, https://github.com/HzaCode/pyDHIS2/issues
Project-URL: Changelog, https://github.com/HzaCode/pyDHIS2/blob/main/CHANGELOG.md
Project-URL: Discussions, https://github.com/HzaCode/pyDHIS2/discussions
Classifier: Development Status :: 4 - Beta
Classifier: Intended Audience :: Developers
Classifier: Intended Audience :: Healthcare Industry
Classifier: License :: OSI Approved :: Apache Software License
Classifier: Programming Language :: Python :: 3
Classifier: Programming Language :: Python :: 3.9
Classifier: Programming Language :: Python :: 3.10
Classifier: Programming Language :: Python :: 3.11
Classifier: Topic :: Software Development :: Libraries :: Python Modules
Classifier: Topic :: Scientific/Engineering :: Medical Science Apps.
Requires-Python: >=3.9
License-File: LICENSE
Requires-Dist: aiohttp<4.0.0,>=3.8.0
Requires-Dist: aiofiles<26.0.0,>=23.0.0
Requires-Dist: aiolimiter<2.0.0,>=1.0.0
Requires-Dist: tenacity<10.0.0,>=8.0.0
Requires-Dist: pandas<3.0.0,>=1.5.0
Requires-Dist: pyarrow<22.0.0,>=10.0.0
Requires-Dist: numpy<3.0.0,>=1.20.0
Requires-Dist: pydantic<3.0.0,>=2.0.0
Requires-Dist: pyyaml<7.0,>=6.0
Requires-Dist: click<9.0.0,>=8.0.0
Requires-Dist: typer<1.0.0,>=0.9.0
Requires-Dist: cookiecutter<3.0.0,>=2.1.0
Requires-Dist: opentelemetry-api<2.0.0,>=1.15.0
Requires-Dist: opentelemetry-sdk<2.0.0,>=1.15.0
Requires-Dist: opentelemetry-exporter-jaeger-thrift<2.0.0,>=1.15.0
Requires-Dist: opentelemetry-exporter-prometheus<1.0.0,>=0.36b0
Requires-Dist: opentelemetry-instrumentation-aiohttp-client<1.0.0,>=0.36b0
Provides-Extra: dev
Requires-Dist: pytest<9.0.0,>=7.0.0; extra == "dev"
Requires-Dist: pytest-asyncio<1.0.0,>=0.21.0; extra == "dev"
Requires-Dist: pytest-mock<4.0.0,>=3.10.0; extra == "dev"
Requires-Dist: pytest-cov<6.0.0,>=4.0.0; extra == "dev"
Requires-Dist: ruff<1.0.0,>=0.1.0; extra == "dev"
Dynamic: license-file
